querygym/__init__.py
querygym/__main__.py
querygym/cli.py
querygym/prompt_bank.yaml
querygym/adapters/__init__.py
querygym/adapters/pyserini_adapter.py
querygym/adapters/pyterrier_adapter.py
querygym/config/defaults.yaml
querygym/core/base.py
querygym/core/llm.py
querygym/core/prompts.py
querygym/core/registry.py
querygym/core/runner.py
querygym/core/searcher.py
querygym/core/searcher_wrappers.py
querygym/core/utils.py
querygym/data/dataloader.py
querygym/loaders/__init__.py
querygym/loaders/beir.py
querygym/loaders/msmarco.py
querygym/methods/__init__.py
querygym/methods/csqe.py
querygym/methods/genqr.py
querygym/methods/genqr_ensemble.py
querygym/methods/lamer.py
querygym/methods/mugi.py
querygym/methods/qa_expand.py
querygym/methods/query2doc.py
querygym/methods/query2e.py
querygym-0.1.5.dist-info/licenses/LICENSE
querygym-0.1.5.dist-info/METADATA
querygym-0.1.5.dist-info/WHEEL
querygym-0.1.5.dist-info/entry_points.txt
querygym-0.1.5.dist-info/top_level.txt
querygym-0.1.5.dist-info/RECORD
