Metadata-Version: 2.4
Name: querygym
Version: 0.1.5
Summary: LLM-based Query Reformulation Toolkit
Author-email: Radin Hamidi Rad <radin.h@gmail.com>, Amin Bigdeli <aminbigdeli97@gmail.com>, Mert Incesu <mert.incesu03@gmail.com>, Negar Arabzadeh <ngr.arabzadeh@gmail.com>
License: Apache-2.0
Project-URL: Homepage, https://github.com/ls3-lab/QueryGym
Project-URL: Documentation, https://github.com/ls3-lab/QueryGym/blob/main/README.md
Project-URL: Repository, https://github.com/ls3-lab/QueryGym
Project-URL: Issues, https://github.com/ls3-lab/QueryGym/issues
Keywords: information-retrieval,query-reformulation,llm,nlp
Classifier: Development Status :: 3 - Alpha
Classifier: Intended Audience :: Science/Research
Classifier: License :: OSI Approved :: Apache Software License
Classifier: Programming Language :: Python :: 3
Classifier: Programming Language :: Python :: 3.9
Classifier: Programming Language :: Python :: 3.10
Classifier: Programming Language :: Python :: 3.11
Classifier: Programming Language :: Python :: 3.12
Classifier: Topic :: Scientific/Engineering :: Artificial Intelligence
Requires-Python: >=3.9
License-File: LICENSE
Requires-Dist: typer>=0.12.3
Requires-Dist: pyyaml>=6.0.1
Requires-Dist: openai>=1.40.0
Requires-Dist: tqdm>=4.65.0
Provides-Extra: hf
Requires-Dist: datasets>=2.20.0; extra == "hf"
Provides-Extra: beir
Requires-Dist: beir>=2.0.0; extra == "beir"
Provides-Extra: pyserini
Requires-Dist: pyserini>=0.22.0; extra == "pyserini"
Provides-Extra: dev
Requires-Dist: pytest>=7.4.0; extra == "dev"
Requires-Dist: pytest-cov>=4.1.0; extra == "dev"
Requires-Dist: pytest-mock>=3.11.0; extra == "dev"
Requires-Dist: black>=23.0.0; extra == "dev"
Requires-Dist: ruff>=0.1.0; extra == "dev"
Requires-Dist: mypy>=1.5.0; extra == "dev"
Requires-Dist: mkdocs>=1.5.0; extra == "dev"
Requires-Dist: mkdocs-material>=9.0.0; extra == "dev"
Requires-Dist: mkdocstrings[python]>=0.23.0; extra == "dev"
Provides-Extra: all
Requires-Dist: datasets>=2.20.0; extra == "all"
Requires-Dist: beir>=2.0.0; extra == "all"
Requires-Dist: pyserini>=0.22.0; extra == "all"
Dynamic: license-file
